sdg_hub/__init__.py
sdg_hub/_version.py
sdg_hub/py.typed
sdg_hub/core/__init__.py
sdg_hub/core/blocks/__init__.py
sdg_hub/core/blocks/base.py
sdg_hub/core/blocks/registry.py
sdg_hub/core/blocks/filtering/__init__.py
sdg_hub/core/blocks/filtering/column_value_filter.py
sdg_hub/core/blocks/llm/__init__.py
sdg_hub/core/blocks/llm/error_handler.py
sdg_hub/core/blocks/llm/llm_chat_block.py
sdg_hub/core/blocks/llm/llm_response_extractor_block.py
sdg_hub/core/blocks/llm/prompt_builder_block.py
sdg_hub/core/blocks/llm/text_parser_block.py
sdg_hub/core/blocks/transform/__init__.py
sdg_hub/core/blocks/transform/duplicate_columns.py
sdg_hub/core/blocks/transform/index_based_mapper.py
sdg_hub/core/blocks/transform/json_structure_block.py
sdg_hub/core/blocks/transform/melt_columns.py
sdg_hub/core/blocks/transform/rename_columns.py
sdg_hub/core/blocks/transform/text_concat.py
sdg_hub/core/blocks/transform/uniform_col_val_setter.py
sdg_hub/core/flow/__init__.py
sdg_hub/core/flow/base.py
sdg_hub/core/flow/checkpointer.py
sdg_hub/core/flow/metadata.py
sdg_hub/core/flow/registry.py
sdg_hub/core/flow/validation.py
sdg_hub/core/utils/__init__.py
sdg_hub/core/utils/datautils.py
sdg_hub/core/utils/error_handling.py
sdg_hub/core/utils/flow_id_words.yaml
sdg_hub/core/utils/flow_identifier.py
sdg_hub/core/utils/flow_metrics.py
sdg_hub/core/utils/logger_config.py
sdg_hub/core/utils/path_resolution.py
sdg_hub/core/utils/time_estimator.py
sdg_hub/core/utils/yaml_utils.py
sdg_hub/flows/evaluation/rag/__init__.py
sdg_hub/flows/evaluation/rag/answer_generation.yaml
sdg_hub/flows/evaluation/rag/conceptual_qa_generation.yaml
sdg_hub/flows/evaluation/rag/context_extraction.yaml
sdg_hub/flows/evaluation/rag/flow.yaml
sdg_hub/flows/evaluation/rag/groundedness_critic.yaml
sdg_hub/flows/evaluation/rag/question_evolution.yaml
sdg_hub/flows/evaluation/rag/topic_generation.yaml
sdg_hub/flows/qa_generation/document_grounded_qa/enhanced_multi_summary_qa/__init__.py
sdg_hub-0.7.3.dist-info/licenses/LICENSE
sdg_hub-0.7.3.dist-info/METADATA
sdg_hub-0.7.3.dist-info/WHEEL
sdg_hub-0.7.3.dist-info/top_level.txt
sdg_hub-0.7.3.dist-info/RECORD
