Metadata-Version: 2.4
Name: sdg_hub
Version: 0.7.3
Summary: Synthetic Data Generation
Author-email: Red Hat AI Innovation <abhandwa@redhat.com>
License: Apache-2.0
Project-URL: homepage, https://ai-innovation.team/
Project-URL: source, https://github.com/Red-Hat-AI-Innovation-Team/sdg_hub
Project-URL: issues, https://github.com/Red-Hat-AI-Innovation-Team/sdg_hub/issues
Classifier: Environment :: Console
Classifier: License :: OSI Approved :: Apache Software License
Classifier: License :: OSI Approved :: MIT License
Classifier: Operating System :: MacOS :: MacOS X
Classifier: Operating System :: POSIX :: Linux
Classifier: Topic :: Scientific/Engineering :: Artificial Intelligence
Classifier: Programming Language :: Python :: 3
Classifier: Programming Language :: Python :: 3.9
Classifier: Programming Language :: Python :: 3.10
Classifier: Programming Language :: Python :: 3.11
Classifier: Programming Language :: Python :: 3.12
Classifier: Programming Language :: Python :: Implementation :: CPython
Requires-Python: >=3.10
License-File: LICENSE
Requires-Dist: click<9.0.0,>=8.1.7
Requires-Dist: datasets>=4.0.0
Requires-Dist: httpx<1.0.0,>=0.25.0
Requires-Dist: jinja2
Requires-Dist: litellm<2.0.0,>=1.73.0
Requires-Dist: rich
Requires-Dist: pandas
Requires-Dist: pydantic<3.0.0,>=2.0.0
Requires-Dist: python-dotenv<2.0.0,>=1.0.0
Requires-Dist: tenacity!=8.4.0,>=8.3.0
Requires-Dist: tqdm<5.0.0,>=4.66.2
Provides-Extra: dev
Requires-Dist: pre-commit<4.0,>=3.0.4; extra == "dev"
Requires-Dist: pylint<4.0,>=2.16.2; extra == "dev"
Requires-Dist: pylint-pydantic; extra == "dev"
Requires-Dist: pytest; extra == "dev"
Requires-Dist: pytest-asyncio; extra == "dev"
Requires-Dist: pytest-cov; extra == "dev"
Requires-Dist: pytest-html; extra == "dev"
Requires-Dist: tox<5,>=4.4.2; extra == "dev"
Requires-Dist: ruff; extra == "dev"
Requires-Dist: pytest-env; extra == "dev"
Requires-Dist: nbconvert>=7.0.0; extra == "dev"
Provides-Extra: integration
Requires-Dist: nest-asyncio; extra == "integration"
Provides-Extra: examples
Requires-Dist: tabulate>=0.9.0; extra == "examples"
Requires-Dist: transformers>=4.37.0; extra == "examples"
Requires-Dist: langchain-text-splitters; extra == "examples"
Requires-Dist: docling>=2.3.0; extra == "examples"
Requires-Dist: scikit-learn; extra == "examples"
Requires-Dist: polars; extra == "examples"
Requires-Dist: matplotlib; extra == "examples"
Requires-Dist: spacy; extra == "examples"
Requires-Dist: nltk; extra == "examples"
Requires-Dist: sentence-transformers; extra == "examples"
Requires-Dist: instructor; extra == "examples"
Requires-Dist: fastapi; extra == "examples"
Requires-Dist: ipykernel; extra == "examples"
Dynamic: license-file
